stickymeta/__init__.py
stickymeta/decorator.py
stickymeta/decorators.py
stickymeta/middleware.py
stickymeta/middlewares.py
stickymeta-0.0.5.dist-info/DESCRIPTION.rst
stickymeta-0.0.5.dist-info/METADATA
stickymeta-0.0.5.dist-info/metadata.json
stickymeta-0.0.5.dist-info/RECORD
stickymeta-0.0.5.dist-info/top_level.txt
stickymeta-0.0.5.dist-info/WHEEL
