Metadata-Version: 2.0
Name: stickymeta
Version: 0.0.5
Summary: Handy tools to maintain persistent meta values between requests in Scrapy spiders
Home-page: http://github.com/mizhgun/scrapy_stickymeta
Author: Mikhail Kolganov
Author-email: mikhail.kolganov@gmail.com
License: MIT
Keywords: scrapy
Platform: UNKNOWN
Classifier: Framework :: Scrapy
Classifier: Development Status :: 3 - Alpha
Classifier: Environment :: Console
Classifier: Intended Audience :: Developers
Classifier: License :: OSI Approved :: MIT License
Classifier: Operating System :: OS Independent
Classifier: Programming Language :: Python
Classifier: Programming Language :: Python :: 2
Classifier: Programming Language :: Python :: 2.7
Classifier: Programming Language :: Python :: 3
Classifier: Programming Language :: Python :: 3.3
Classifier: Programming Language :: Python :: 3.4
Classifier: Programming Language :: Python :: 3.5
Classifier: Programming Language :: Python :: 3.6
Classifier: Topic :: Internet :: WWW/HTTP
Classifier: Topic :: Software Development :: Libraries
Classifier: Topic :: Software Development :: Libraries :: Python Modules
Requires-Dist: Scrapy (>=1.0.0)
